av_play/__AV_Common.py
av_play/__AV_Instance.py
av_play/__AV_Interface.py
av_play/__AV_Player.py
av_play/__init__.py
av_play/__utils.py
av_play/audio_filter.py
av_play/fmod_audio_filter.py
av_play/fmod_audio_player.py
av_play/media_info.py
av_play/mpv_audio_filter.py
av_play/mpv_video_player.py
av_play/playlist.py
av_play/video_filter.py
av_play/vlc_audio_filter.py
av_play/vlc_video_player.py
avplay-1.2.1.dist-info/licenses/LICENSE
avplay-1.2.1.dist-info/METADATA
avplay-1.2.1.dist-info/WHEEL
avplay-1.2.1.dist-info/top_level.txt
avplay-1.2.1.dist-info/RECORD
