Metadata-Version: 2.4
Name: AVPlay
Version: 1.2.1
Summary: Audio and video playback library
Home-page: https://github.com/still-standing88/av-play/
Author: still-standing88
License: MIT
Keywords: av-play AVPlay audio video media playback
Classifier: Development Status :: 4 - Beta
Classifier: Intended Audience :: Developers
Classifier: License :: OSI Approved :: MIT License
Classifier: Programming Language :: Python :: 3
Classifier: Programming Language :: Python :: 3.6
Classifier: Programming Language :: Python :: 3.7
Classifier: Programming Language :: Python :: 3.8
Classifier: Programming Language :: Python :: 3.9
Classifier: Programming Language :: Python :: 3.10
Classifier: Topic :: Software Development :: Documentation
Classifier: Topic :: Utilities
Requires-Python: >=3.6
License-File: LICENSE
Requires-Dist: python-mpv
Requires-Dist: python-vlc
Requires-Dist: pyfmodex
Requires-Dist: validators
Requires-Dist: music-tag
Dynamic: author
Dynamic: classifier
Dynamic: description
Dynamic: description-content-type
Dynamic: home-page
Dynamic: keywords
Dynamic: license
Dynamic: license-file
Dynamic: requires-dist
Dynamic: requires-python
Dynamic: summary
